img2speech.py
img2speech-1.0.13.dist-info/LICENSE
img2speech-1.0.13.dist-info/METADATA
img2speech-1.0.13.dist-info/WHEEL
img2speech-1.0.13.dist-info/top_level.txt
img2speech-1.0.13.dist-info/RECORD
