Metadata-Version: 2.1
Name: img2speech
Version: 1.0.13
Summary: Integrated Python package for converting Image to speech
Author: Shreyas P J
Classifier: Programming Language :: Python :: 3
Classifier: License :: OSI Approved :: MIT License
Classifier: Operating System :: OS Independent
Requires-Python: >=3.8
License-File: LICENSE
Requires-Dist: easyocr (==1.6.2)
Requires-Dist: gtts (==2.3.1)
Requires-Dist: langdetect (==1.0.9)
Requires-Dist: pypdfium2 (==4.5.0)
